{
    "keep": {
        "days": true,
        "amount": 30
    },
    "auditLog": "F:\\TeamProject\\WorkStationFlow-X\\logs\\.19738d29505b223516e3a040967a12decfff023d-audit.json",
    "files": [
        {
            "date": 1746619891912,
            "name": "F:\\TeamProject\\WorkStationFlow-X\\logs\\2025-05-07-app.log",
            "hash": "2d2ca13e41c4ef2be418c00afe159f6c14463349418fb8fe15b1b0fe3127083c"
        },
        {
            "date": 1746719254484,
            "name": "F:\\TeamProject\\WorkStationFlow-X\\logs\\2025-05-08-app.log",
            "hash": "d854ffbdd2a0e36713d6cfc8f6872fb3693f268bd19ec2eb58cd23182d8cf695"
        },
        {
            "date": 1746727408134,
            "name": "F:\\TeamProject\\WorkStationFlow-X\\logs\\2025-05-09-app.log",
            "hash": "c5ef7fa4fde06fc1c39bfdb30b0dcedff2236f043a4b83cf53720c6a3110ed70"
        },
        {
            "date": 1746885868045,
            "name": "F:\\TeamProject\\WorkStationFlow-X\\logs\\2025-05-10-app.log",
            "hash": "295f268363129337365036fa116b2526db36d9119120d51e0244af8491955c1a"
        },
        {
            "date": 1746970250202,
            "name": "F:\\TeamProject\\WorkStationFlow-X\\logs\\2025-05-11-app.log",
            "hash": "5f303da10f24a54f38d5818933297bf47ebc9c0f62c8c31e2cde4a456732be0d"
        },
        {
            "date": 1746986609847,
            "name": "F:\\TeamProject\\WorkStationFlow-X\\logs\\2025-05-12-app.log",
            "hash": "a1e1487b4326b6b84100d39611d12f73853a07bb72bc179cabb23e112493cba2"
        },
        {
            "date": 1747146008300,
            "name": "F:\\TeamProject\\WorkStationFlow-X\\logs\\2025-05-13-app.log",
            "hash": "2f1c305cd852d7a71c18ea05e60b995b840fc9c4eac32c0df20197fc8484c7f2"
        },
        {
            "date": 1747317931743,
            "name": "F:\\TeamProject\\WorkStationFlow-X\\logs\\2025-05-15-app.log",
            "hash": "ba3afa6724013a50da3b3b209e80cf69cadeb8c4ad9a5ced9e48c2b561008037"
        },
        {
            "date": 1747332067611,
            "name": "F:\\TeamProject\\WorkStationFlow-X\\logs\\2025-05-16-app.log",
            "hash": "059fd2dcad6559988e3cff387a61827ac02d7e056a40cf814a54375603faef0a"
        },
        {
            "date": 1747746495434,
            "name": "F:\\TeamProject\\WorkStationFlow-X\\logs\\2025-05-20-app.log",
            "hash": "e6a8e81fcb58b63b04d56e08bde3d7d8ac427a3d276cf95003ac22ee155244d7"
        }
    ],
    "hashType": "sha256"
}